README.rst
setup.py
BottleDaemon.egg-info/PKG-INFO
BottleDaemon.egg-info/SOURCES.txt
BottleDaemon.egg-info/dependency_links.txt
BottleDaemon.egg-info/requires.txt
BottleDaemon.egg-info/top_level.txt
bottledaemon/__init__.py
bottledaemon/bottledaemon.py