Metadata-Version: 1.0
Name: BottleDaemon
Version: 0.1.1
Summary: A simple tool to help daemonize bottle applications.
Home-page: UNKNOWN
Author: Jonathan Hood
Author-email: me@jonathanhood.org
License: UNKNOWN
Platform: UNKNOWN
